{
  "title": "Come On My Selector",
  "slug": "come-on-my-selector",
  "artist": "squarepusher",
  "estimated_revenue": "$15K-$65K/year",
  "album": "Big Loada",
  "year": 1998,
  "meaning_summary": "This recording leans on atmosphere, texture, and replayable mood, which makes it durable in listener memory and long-tail streaming.",
  "revenue_drivers": [
    "Playlist and mood-based streaming support repeat listening over long periods.",
    "Steady niche demand and reissue interest can keep the track earning.",
    "Licensing and soundtrack-style use can materially improve the long tail."
  ],
  "related_songs": [
    "my-red-hot-car"
  ]
}
