{
  "title": "Livin' on a Prayer",
  "slug": "livin-on-a-prayer",
  "artist": "bon-jovi",
  "estimated_revenue": "$500K-$1.5M/year",
  "album": "Slippery When Wet",
  "year": 1986,
  "meaning_summary": "This song holds value through a recognizable core riff or chorus, strong emotional payoff, and steady replay.",
  "revenue_drivers": [
    "Classic replay value and catalog streaming keep major rock songs relevant.",
    "Cultural familiarity supports long-tail listener demand.",
    "Sync placements and live-culture recognition help extend the song's revenue life."
  ],
  "related_songs": [
    "wanted-dead-or-alive"
  ],
  "earnings": {
    "gross_track_revenue": "$1.5M-$4.4M/year",
    "artist_or_estate_share": "$500K-$1.5M/year",
    "label_master_share": "$475K-$1.4M/year",
    "publishing_share": "$150K-$450K/year",
    "songwriter_share": "$210K-$630K/year",
    "assumptions": "Estimate keeps the current headline range as the artist-side figure and models gross track, label, publishing, and songwriter lanes from that conservative annual range."
  },
  "ownership": {
    "master_owner": "Likely controlled through the recording label or distributor unless a specific rights sale is known",
    "publishing_owner": "Writer and publisher splits affect the publishing share shown here",
    "catalog_sale_status": "No specific catalog sale adjustment is modeled for this track",
    "notes": "Livin' on a Prayer is modeled from public-facing catalog behavior and conservative rights-split assumptions, not from audited royalty statements."
  }
}
