{
  "name": "Soundgarden",
  "slug": "soundgarden",
  "estimated_income": "$2M-$7M/year",
  "top_songs": ["black-hole-sun", "fell-on-black-days", "outshined"],
  "genre": "Grunge / Hard Rock",
  "country": "United States",
  "active_since": "1984",
  "bio": "Soundgarden's catalog remains commercially relevant through heavy-rock streaming, grunge-era nostalgia, and Chris Cornell's lasting cultural footprint.",
  "notable_for": "Powerful vocal identity, dark heavy-rock songwriting, and core grunge-catalog status.",
  "career_highlight": "Black Hole Sun and other signature tracks remain among the most durable songs from the 1990s grunge wave.",
  "revenue_drivers": [
    "Major grunge songs continue to stream well across rock generations.",
    "Chris Cornell's legacy increases catalog attention and discovery.",
    "Sync and documentary use supports long-tail commercial value."
  ]
}
